modules/__init__.py
modules/activation.py
modules/block.py
modules/conv.py
modules/custom_layers.py
modules/head.py
modules/transformer.py
modules/utils.py
my_modules/HRAMI.py
my_modules/SPDConv.py
my_modules/WTConv.py
my_modules/__init__.py
xl_yolo_pkg-0.1.3.dist-info/LICENSE
xl_yolo_pkg-0.1.3.dist-info/METADATA
xl_yolo_pkg-0.1.3.dist-info/WHEEL
xl_yolo_pkg-0.1.3.dist-info/top_level.txt
xl_yolo_pkg-0.1.3.dist-info/RECORD
